githubfork/__init__.py
githubfork/githubfork.py
PyGithubFork-0.0.2.dist-info/METADATA
PyGithubFork-0.0.2.dist-info/WHEEL
PyGithubFork-0.0.2.dist-info/top_level.txt
PyGithubFork-0.0.2.dist-info/RECORD
